__init__.py
animations/ColorChangingText.py
animations/CustomAnimation.py
animations/LoadingAnimation.py
animations/__init__.py
images/Image.py
images/__init__.py
images/shapes/Circle.py
images/shapes/Decagon.py
images/shapes/Dodecagon.py
images/shapes/Ellipse.py
images/shapes/EquilateralTriangle.py
images/shapes/Hendecagon.py
images/shapes/Heptagon.py
images/shapes/Hexagon.py
images/shapes/Nonogon.py
images/shapes/Octogon.py
images/shapes/Pentagon.py
images/shapes/Rectangle.py
images/shapes/RightTriangle.py
images/shapes/Septagon.py
images/shapes/Square.py
images/shapes/__init__.py
text/GiantText.py
text/__init__.py
utils/BinaryToHexConverter.py
utils/HexDataType.py
utils/HexToASCIIColor.py
utils/HexToBinaryConverter.py
utils/__init__.py
widgets/BooleanSwitch.py
widgets/Checkbox.py
widgets/RadioButton.py
widgets/Slider.py
widgets/__init__.py
cmdguicomponents-0.0.1.dist-info/LICENSE
cmdguicomponents-0.0.1.dist-info/METADATA
cmdguicomponents-0.0.1.dist-info/WHEEL
cmdguicomponents-0.0.1.dist-info/top_level.txt
cmdguicomponents-0.0.1.dist-info/RECORD
