Metadata-Version: 2.1
Name: cmdguicomponents
Version: 0.0.1
Summary: A python library designed 
Author-email: John Ciftcioglu <jk0011gamingg@gmail.com>
Classifier: Programming Language :: Python :: 3
Classifier: License :: OSI Approved :: MIT License
Classifier: Operating System :: OS Independent
Requires-Python: >=3.8
License-File: LICENSE
